llama_deploy/cli/__init__.py
llama_deploy/cli/app.py
llama_deploy/cli/auth/client.py
llama_deploy/cli/client.py
llama_deploy/cli/commands/aliased_group.py
llama_deploy/cli/commands/auth.py
llama_deploy/cli/commands/deployment.py
llama_deploy/cli/commands/dev.py
llama_deploy/cli/commands/env.py
llama_deploy/cli/commands/init.py
llama_deploy/cli/commands/pkg.py
llama_deploy/cli/commands/serve.py
llama_deploy/cli/config/_config.py
llama_deploy/cli/config/_migrations.py
llama_deploy/cli/config/auth_service.py
llama_deploy/cli/config/env_service.py
llama_deploy/cli/config/migrations/0001_init.sql
llama_deploy/cli/config/migrations/0002_add_auth_fields.sql
llama_deploy/cli/config/migrations/__init__.py
llama_deploy/cli/config/schema.py
llama_deploy/cli/debug.py
llama_deploy/cli/env.py
llama_deploy/cli/interactive_prompts/session_utils.py
llama_deploy/cli/interactive_prompts/utils.py
llama_deploy/cli/options.py
llama_deploy/cli/pkg/__init__.py
llama_deploy/cli/pkg/defaults.py
llama_deploy/cli/pkg/options.py
llama_deploy/cli/pkg/utils.py
llama_deploy/cli/py.typed
llama_deploy/cli/styles.py
llama_deploy/cli/textual/deployment_form.py
llama_deploy/cli/textual/deployment_help.py
llama_deploy/cli/textual/deployment_monitor.py
llama_deploy/cli/textual/git_validation.py
llama_deploy/cli/textual/github_callback_server.py
llama_deploy/cli/textual/llama_loader.py
llama_deploy/cli/textual/secrets_form.py
llama_deploy/cli/textual/styles.tcss
llama_deploy/cli/utils/env_inject.py
llama_deploy/cli/utils/redact.py
llama_deploy/cli/utils/retry.py
llama_deploy/cli/utils/version.py
llamactl-0.4.1.dist-info/WHEEL
llamactl-0.4.1.dist-info/entry_points.txt
llamactl-0.4.1.dist-info/METADATA
llamactl-0.4.1.dist-info/RECORD
