Metadata-Version: 2.3
Name: llamactl
Version: 0.4.1
Summary: A command-line interface for managing LlamaDeploy projects and deployments
Author: Adrian Lyjak
Author-email: Adrian Lyjak <adrianlyjak@gmail.com>
License: MIT
Requires-Dist: llama-deploy-core[client]>=0.4.1,<0.5.0
Requires-Dist: llama-deploy-appserver>=0.4.1,<0.5.0
Requires-Dist: vibe-llama-core>=0.1.0
Requires-Dist: rich>=13.0.0
Requires-Dist: questionary>=2.0.0
Requires-Dist: click>=8.2.1
Requires-Dist: python-dotenv>=1.0.0
Requires-Dist: tenacity>=9.1.2
Requires-Dist: textual>=6.0.0
Requires-Dist: aiohttp>=3.12.14
Requires-Dist: copier>=9.10.2
Requires-Dist: pyjwt[crypto]>=2.10.1
Requires-Dist: typing-extensions>=4.15.0
Requires-Dist: typing-extensions>=4.15.0 ; python_full_version < '3.11'
Requires-Python: >=3.10, <4
